septentrion/__init__.py
septentrion/__main__.py
septentrion/cli.py
septentrion/configuration.py
septentrion/core.py
septentrion/db.py
septentrion/exceptions.py
septentrion/files.py
septentrion/lib.py
septentrion/metadata.py
septentrion/migration.py
septentrion/runner.py
septentrion/style.py
septentrion/utils.py
septentrion/versions.py
septentrion-0.7.8.dist-info/entry_points.txt
septentrion-0.7.8.dist-info/LICENSE.rst
septentrion-0.7.8.dist-info/WHEEL
septentrion-0.7.8.dist-info/METADATA
septentrion-0.7.8.dist-info/RECORD
