Metadata-Version: 2.1
Name: septentrion
Version: 0.7.8
Summary: Python CLI tool for managing and executing hand-written PostgreSQL migrations
Home-page: https://septentrion.readthedocs.io/en/latest/
License: MIT
Keywords: postgresql,migration,psql
Author: Python UKG Community
Author-email: peopledoc-python@ukg.com
Requires-Python: >=3.7,<4.0
Classifier: Development Status :: 5 - Production/Stable
Classifier: Intended Audience :: Developers
Classifier: License :: OSI Approved :: MIT License
Classifier: Programming Language :: Python :: 3
Classifier: Programming Language :: Python :: 3.10
Classifier: Programming Language :: Python :: 3.7
Classifier: Programming Language :: Python :: 3.8
Classifier: Programming Language :: Python :: 3.9
Provides-Extra: psycopg2
Provides-Extra: psycopg2_binary
Requires-Dist: click
Requires-Dist: colorama
Requires-Dist: importlib-metadata
Requires-Dist: psycopg2; extra == "psycopg2"
Requires-Dist: psycopg2_binary; extra == "psycopg2_binary"
Requires-Dist: sqlparse
Project-URL: Documentation, https://septentrion.readthedocs.io/en/latest/
Project-URL: Repository, https://github.com/peopledoc/septentrion
